bounded_models/__init__.py
bounded_models/_handlers.py
bounded_models/_model.py
bounded_models/_overrides.py
bounded_models/_registry.py
bounded_models/py.typed
bounded_models-0.0.5.dist-info/licenses/LICENSE
bounded_models-0.0.5.dist-info/WHEEL
bounded_models-0.0.5.dist-info/METADATA
bounded_models-0.0.5.dist-info/RECORD
