Metadata-Version: 2.4
Name: bounded-models
Version: 0.0.5
Summary: A framework to check if Pydantic models are bounded
Author: Shunichiro Nomura
Author-email: Shunichiro Nomura <nomura@space.t.u-tokyo.ac.jp>
License-Expression: MIT
License-File: LICENSE
Classifier: Development Status :: 3 - Alpha
Classifier: License :: OSI Approved :: MIT License
Classifier: Programming Language :: Python
Classifier: Programming Language :: Python :: 3 :: Only
Classifier: Programming Language :: Python :: 3.13
Classifier: Typing :: Typed
Requires-Dist: more-itertools>=10.7.0
Requires-Dist: pydantic>=2.11.7
Requires-Python: >=3.13
Project-URL: Documentation, https://shunichironomura.github.io/bounded-models/
Project-URL: Issues, https://github.com/shunichironomura/bounded-models/issues
Project-URL: Repository, https://github.com/shunichironomura/bounded-models
